LICENSE
README.md
souk/__init__.py
souk/htcondor_helper.py
souk/system/arch_info.py
souk/util/__init__.py
souk/util/cli/__init__.py
souk/util/cli/arg_string.py
souk/util/cli/ini_formatter.py
souk-0.4.1.dist-info/LICENSE
souk-0.4.1.dist-info/METADATA
souk-0.4.1.dist-info/WHEEL
souk-0.4.1.dist-info/entry_points.txt
souk-0.4.1.dist-info/RECORD
